odoo/addons/base_ubl/README.rst
odoo/addons/base_ubl/__init__.py
odoo/addons/base_ubl/__manifest__.py
odoo/addons/base_ubl/data/xsd-2.0/common/CCTS_CCT_SchemaModule-2.0.xsd
odoo/addons/base_ubl/data/xsd-2.0/common/CodeList_CurrencyCode_ISO_7_04.xsd
odoo/addons/base_ubl/data/xsd-2.0/common/CodeList_LanguageCode_ISO_7_04.xsd
odoo/addons/base_ubl/data/xsd-2.0/common/CodeList_MIMEMediaTypeCode_IANA_7_04.xsd
odoo/addons/base_ubl/data/xsd-2.0/common/CodeList_UnitCode_UNECE_7_04.xsd
odoo/addons/base_ubl/data/xsd-2.0/common/UBL-CommonAggregateComponents-2.0.xsd
odoo/addons/base_ubl/data/xsd-2.0/common/UBL-CommonBasicComponents-2.0.xsd
odoo/addons/base_ubl/data/xsd-2.0/common/UBL-CommonExtensionComponents-2.0.xsd
odoo/addons/base_ubl/data/xsd-2.0/common/UBL-CoreComponentParameters-2.0.xsd
odoo/addons/base_ubl/data/xsd-2.0/common/UBL-ExtensionContentDatatype-2.0.xsd
odoo/addons/base_ubl/data/xsd-2.0/common/UBL-QualifiedDatatypes-2.0.xsd
odoo/addons/base_ubl/data/xsd-2.0/common/UnqualifiedDataTypeSchemaModule-2.0.xsd
odoo/addons/base_ubl/data/xsd-2.0/maindoc/UBL-ApplicationResponse-2.0.xsd
odoo/addons/base_ubl/data/xsd-2.0/maindoc/UBL-AttachedDocument-2.0.xsd
odoo/addons/base_ubl/data/xsd-2.0/maindoc/UBL-BillOfLading-2.0.xsd
odoo/addons/base_ubl/data/xsd-2.0/maindoc/UBL-Catalogue-2.0.xsd
odoo/addons/base_ubl/data/xsd-2.0/maindoc/UBL-CatalogueDeletion-2.0.xsd
odoo/addons/base_ubl/data/xsd-2.0/maindoc/UBL-CatalogueItemSpecificationUpdate-2.0.xsd
odoo/addons/base_ubl/data/xsd-2.0/maindoc/UBL-CataloguePricingUpdate-2.0.xsd
odoo/addons/base_ubl/data/xsd-2.0/maindoc/UBL-CatalogueRequest-2.0.xsd
odoo/addons/base_ubl/data/xsd-2.0/maindoc/UBL-CertificateOfOrigin-2.0.xsd
odoo/addons/base_ubl/data/xsd-2.0/maindoc/UBL-CreditNote-2.0.xsd
odoo/addons/base_ubl/data/xsd-2.0/maindoc/UBL-DebitNote-2.0.xsd
odoo/addons/base_ubl/data/xsd-2.0/maindoc/UBL-DespatchAdvice-2.0.xsd
odoo/addons/base_ubl/data/xsd-2.0/maindoc/UBL-ForwardingInstructions-2.0.xsd
odoo_addon_base_ubl-18.0.1.0.0.3.dist-info/METADATA
odoo_addon_base_ubl-18.0.1.0.0.3.dist-info/WHEEL
odoo_addon_base_ubl-18.0.1.0.0.3.dist-info/top_level.txt
odoo_addon_base_ubl-18.0.1.0.0.3.dist-info/RECORD
