Metadata-Version: 2.1
Name: odoo-addon-base_ubl
Version: 18.0.1.0.0.3
Requires-Python: >=3.10
Requires-Dist: odoo==18.0.*
Summary: Base module for Universal Business Language (UBL)
Home-page: https://github.com/OCA/edi
License: AGPL-3
Author: Akretion,Onestein,Camptocamp,Odoo Community Association (OCA)
Author-email: support@odoo-community.org
Classifier: Programming Language :: Python
Classifier: Framework :: Odoo
Classifier: Framework :: Odoo :: 18.0
Classifier: License :: OSI Approved :: GNU Affero General Public License v3
